falcon/__init__.py
falcon/common.py
falcon/encoding.py
falcon/falcon.py
falcon/ffsampling.py
falcon/fft.py
falcon/fft_constants.py
falcon/ntrugen.py
falcon/ntt.py
falcon/ntt_constants.py
falcon/profile_action.py
falcon/rng.py
falcon/samplerz.py
falcon/scripts/README.md
falcon/scripts/__init__.py
falcon/scripts/generate_constants.sage
falcon/scripts/parameters.py
falcon/scripts/saga.py
falcon/scripts/samplerz_KAT1024.py
falcon/scripts/samplerz_KAT512.py
falcon/scripts/sign_KAT.py
falcon/test.py
falcon_digital_signature-0.9.3.dist-info/LICENSE
falcon_digital_signature-0.9.3.dist-info/METADATA
falcon_digital_signature-0.9.3.dist-info/WHEEL
falcon_digital_signature-0.9.3.dist-info/RECORD
