Metadata-Version: 2.1
Name: falcon-digital-signature
Version: 0.9.3
Summary: A python implementation of the signature scheme Falcon with packaging 
License: MIT
Author: Thomas Prest
Author-email: thomas.prest@ens.fr
Requires-Python: >=3.7,<3.14
Classifier: License :: OSI Approved :: MIT License
Classifier: Programming Language :: Python :: 3
Classifier: Programming Language :: Python :: 3.7
Classifier: Programming Language :: Python :: 3.8
Classifier: Programming Language :: Python :: 3.9
Classifier: Programming Language :: Python :: 3.10
Classifier: Programming Language :: Python :: 3.11
Classifier: Programming Language :: Python :: 3.12
Classifier: Programming Language :: Python :: 3.13
Requires-Dist: numpy (>=1.21.5,<2.0.0) ; python_version >= "3.7" and python_version < "3.9"
Requires-Dist: numpy (>=1.26.0,<2.0.0) ; python_version >= "3.9" and python_version < "3.11"
Requires-Dist: numpy (>=2.2.0,<3.0.0) ; python_version >= "3.11" and python_version < "3.14"
Requires-Dist: pycryptodome (>=3.16.0,<4.0.0)
